<?xml version="1.0" encoding="utf-8"?>
<LanguageData>

  <!-- SPECIAL: These Recipes from makeable ThingDefs (which include <recipeMaker>), generated by RimTrans -->


  <!-- Recipe Users: TableMachining -->
  
  <Make_Gun_SKCoco.label>制作Coco的挎包</Make_Gun_SKCoco.label>
  <Make_Gun_SKCoco.description>制作Coco的挎包</Make_Gun_SKCoco.description>
  <Make_Gun_SKCoco.jobString>制作Coco的挎包中</Make_Gun_SKCoco.jobString>

  <Make_Gun_SKCrescentRoseRifle.label>制作新月玫瑰(Crescent Rose)</Make_Gun_SKCrescentRoseRifle.label>
  <Make_Gun_SKCrescentRoseRifle.description>制作新月玫瑰(Crescent Rose)</Make_Gun_SKCrescentRoseRifle.description>
  <Make_Gun_SKCrescentRoseRifle.jobString>制作新月玫瑰(Crescent Rose)中</Make_Gun_SKCrescentRoseRifle.jobString>
  
  <Make_Gun_SKEmberCelica.label>制作灰烬天堂(Ember Celica)</Make_Gun_SKEmberCelica.label>
  <Make_Gun_SKEmberCelica.description>制作灰烬天堂(Ember Celica)</Make_Gun_SKEmberCelica.description>
  <Make_Gun_SKEmberCelica.jobString>制作灰烬天堂(Ember Celica)中</Make_Gun_SKEmberCelica.jobString>
  
  <Make_Gun_SKMagnhild.label>制作神威战锤(Magnhild)</Make_Gun_SKMagnhild.label>
  <Make_Gun_SKMagnhild.description>制作神威战锤(Magnhild)</Make_Gun_SKMagnhild.description>
  <Make_Gun_SKMagnhild.jobString>制作神威战锤(Magnhild)中</Make_Gun_SKMagnhild.jobString>

  
  <Make_Gun_SKStormFlower.label>制作洛神之枪</Make_Gun_SKStormFlower.label>
  <Make_Gun_SKStormFlower.description>制作洛神之枪</Make_Gun_SKStormFlower.description>
  <Make_Gun_SKStormFlower.jobString>制作洛神之枪中</Make_Gun_SKStormFlower.jobString>
  
</LanguageData>